[
  {
    "title": "Winterchaos in Chemnitz am 7.2.2026",
    "link": "https://events.ccc.de/2026/01/30/winterchaos-2026/",
    "pubDate": "2026-01-30T16:35:00.000Z",
    "content": "TL;DR 7.2.2026 im Lokomov (Augustusburger Straße 102, Chemnitz) Vorträge, Lightning Talks, Workshops (tbd.) und Abendunterhaltung chch.it/Winterchaos ; CfP inzwischen geschlossen Am 7. Februar laden wir euch nach Chemnitz zum gemütlichen Winterchaos ein. Zwischen Retro-Computern, Waffeln und USB-C-Schnittstellen treffen wir uns im Lokomov in der Augustusburger Straße 102 zu einem Nachmittag und Abend mit Vorträgen, Lightning Talks und etwas Abendunterhaltung. Bei Gelegenheit könnt ihr außerdem u...",
    "creator": "",
    "sourceTitle": "CCC Event Blog",
    "sheetCategory": "(Avoin) data + teknologia",
    "enforcedImage": null,
    "sourceDescription": "Recent content on CCC Event Blog",
    "sourceLogo": "https://www.google.com/s2/favicons?sz=128&domain=events.ccc.de",
    "originalRssUrl": "https://events.ccc.de/feed"
  }
]