[
  {
    "title": "EU viikossa 22/2026: Sisämarkkinat | Teollisuus | Humanitaarinen apu",
    "link": "https://www.eurooppalainensuomi.fi/eu-viikossa-22-2026-sisamarkkinat-teollisuus-humanitaarinen-apu",
    "pubDate": "2026-05-27T09:41:58.000Z",
    "content": "<html><head></head><body><p>Brysselissä ei järjestetä tällä viikolla Euroopan parlamentin kokouksia, sillä viikko on varattu parlamentin ulkoiselle toiminnalle. Tiistaina maatalous- ja kalastusneuvoston ministerit keskustelevat lannoitteista, maatalouskaupasta ja niihin liittyvästä markkinakehityksestä. Samana päivänä yleisten asioiden neuvosto käsittelee muun muassa EU:n ja Yhdistyneen kuningaskunnan suhteita sekä ulkomailla asuvien EU-kansalaisten äänioikeuksia.</p>\n\n\n\n<p>Keskiviikkona komissaarit kokoontuvat Brysselissä esitelläkseen uuden tiedonannon humanitaarisesta avusta. Torstaina kilpailukykyneuvoston ministerit, sisämarkkina- ja teollisuusasioiden kokoonpanossa, keskustelevat teollisuuspolitiikasta, kestävästä matkailusta sekä Lähi-idän kriisin vaikutuksista matkailualaan. Perjantaina komissaarit kokoontuvat Brysselissä periaatekeskusteluun EU:n ja Kiinan suhteista.</p>\n\n\n\n<h3><strong>Euroopan parlamentti</strong></h3>\n\n\n\n<p>Brysselissä ei järjestetä tällä viikolla parlamentin kokouksia, sillä viikko on varattu parlamentin ulkoiselle toiminnalle.</p>\n\n\n\n<h3><strong>Euroopan komissio</strong></h3>\n\n\n\n<p>Tiistaina komissaari Piotr Serafin tapaa Suomen Eurooppa- ja omistajaohjausministerin Joakim St</p></body></html>",
    "snippet": "Brysselissä ei järjestetä tällä viikolla Euroopan parlamentin kokouksia, sillä viikko on varattu parlamentin ulkoiselle toiminnalle. Tiistaina maatalous- ja kalastusneuvoston ministerit keskustelevat ",
    "creator": "Admin",
    "sourceTitle": "Eurooppalainen Suomi",
    "sheetCategory": "Politics + Public sector",
    "enforcedImage": null,
    "sourceDescription": "Parempaa Eurooppaa rakentamassa",
    "sourceLogo": "https://www.eurooppalainensuomi.fi/wp-content/uploads/2023/08/cropped-Flag_of_Europe.svg_-32x32.png",
    "lang": "fi",
    "scope": "Europe",
    "isDarkLogo": false,
    "originalRssUrl": "https://www.eurooppalainensuomi.fi/?feed=rss2"
  }
]