[
  {
    "title": "January 2026 Newsletter | Knowledge Rights 21",
    "link": "https://mailchi.mp/knowledgerights21/jan-2026-kr21-newsletter",
    "pubDate": "2026-02-02T14:15:00.000Z",
    "content": "<!----><!--[if !gte mso 9]><!----><html><head></head><body><span class=\"mcnPreviewText\">KR21 unfair contract terms insights, upcoming events, Kluwer Copyright Blog post on SPR, LIBER cascading grants, KR21 reflections &amp; community updates</span><!--<![endif]-->\n<!---->\n<div>͏ ‌ &nbsp;    ͏ ‌ &nbsp;    ͏ ‌ &nbsp;    ͏ ‌ &nbsp;    ͏ ‌ &nbsp;    ͏ ‌ &nbsp;    ͏ ‌ &nbsp;    ͏ ‌ &nbsp;    ͏ ‌ &nbsp;    ͏ ‌ &nbsp;    ͏ ‌ &nbsp;    ͏ ‌ &nbsp;    ͏ ‌ &nbsp;    ͏ ‌ &nbsp;    ͏ ‌ &nbsp;    ͏ ‌ &nbsp;  ...",
    "creator": "",
    "sourceTitle": "Knowledge Rights 21 Archive Feed",
    "sheetCategory": "Digital policy + rights",
    "enforcedImage": "https://mcusercontent.com/5c5e54d49b987a66678f4182c/images/fda108a9-e438-ccce-8b7a-129e694b7392.png",
    "sourceDescription": "",
    "sourceLogo": "https://www.google.com/s2/favicons?sz=128&domain=us14.campaign-archive.com",
    "lang": "en",
    "scope": "World",
    "isDarkLogo": false,
    "originalRssUrl": "https://us14.campaign-archive.com/feed?u=5c5e54d49b987a66678f4182c&id=2769f0ee4a"
  },
  {
    "title": "December 2025 Newsletter | Knowledge Rights 21",
    "link": "https://mailchi.mp/knowledgerights21/dec-2025-kr21-newsletter",
    "pubDate": "2025-12-18T10:15:00.000Z",
    "content": "<!----><!--[if !gte mso 9]><!----><html><head></head><body><span class=\"mcnPreviewText\">Feb '26 European Rights Retention CoP meeting, ERA Act webinar recording, Tech Policy Press &amp; Times Higher Education op-eds, 5th Freedom report &amp; more</span><!--<![endif]-->\n<!---->\n<div>͏ ‌ &nbsp;    ͏ ‌ &nbsp;    ͏ ‌ &nbsp;    ͏ ‌ &nbsp;    ͏ ‌ &nbsp;    ͏ ‌ &nbsp;    ͏ ‌ &nbsp;    ͏ ‌ &nbsp;    ͏ ‌ &nbsp;    ͏ ‌ &nbsp;    ͏ ‌ &nbsp;    ͏ ‌ &nbsp;    ͏ ‌ &nbsp;    ͏ ‌ &nbsp;    ͏ ‌ &nbsp;    ͏ ‌ &nb...",
    "creator": "",
    "sourceTitle": "Knowledge Rights 21 Archive Feed",
    "sheetCategory": "Digital policy + rights",
    "enforcedImage": "https://mcusercontent.com/5c5e54d49b987a66678f4182c/images/fda108a9-e438-ccce-8b7a-129e694b7392.png",
    "sourceDescription": "",
    "sourceLogo": "https://www.google.com/s2/favicons?sz=128&domain=us14.campaign-archive.com",
    "lang": "en",
    "scope": "World",
    "isDarkLogo": false,
    "originalRssUrl": "https://us14.campaign-archive.com/feed?u=5c5e54d49b987a66678f4182c&id=2769f0ee4a"
  },
  {
    "title": "November 2025 Newsletter | Knowledge Rights 21",
    "link": "https://mailchi.mp/knowledgerights21/nov-2025-kr21-newsletter",
    "pubDate": "2025-12-01T15:15:00.000Z",
    "content": "<!----><!--[if !gte mso 9]><!----><html><head></head><body><span class=\"mcnPreviewText\">New KR21 supported report on Greece, upcoming 10 December ERA Act webinar, KR21 reflections, community updates, and resources</span><!--<![endif]-->\n<!---->\n<div>͏ ‌ &nbsp;    ͏ ‌ &nbsp;    ͏ ‌ &nbsp;    ͏ ‌ &nbsp;    ͏ ‌ &nbsp;    ͏ ‌ &nbsp;    ͏ ‌ &nbsp;    ͏ ‌ &nbsp;    ͏ ‌ &nbsp;    ͏ ‌ &nbsp;    ͏ ‌ &nbsp;    ͏ ‌ &nbsp;    ͏ ‌ &nbsp;    ͏ ‌ &nbsp;    ͏ ‌ &nbsp;    ͏ ‌ &nbsp;    ͏ ‌ &nbsp;    ͏ ‌ &nbsp;  ...",
    "creator": "",
    "sourceTitle": "Knowledge Rights 21 Archive Feed",
    "sheetCategory": "Digital policy + rights",
    "enforcedImage": "https://mcusercontent.com/5c5e54d49b987a66678f4182c/images/fda108a9-e438-ccce-8b7a-129e694b7392.png",
    "sourceDescription": "",
    "sourceLogo": "https://www.google.com/s2/favicons?sz=128&domain=us14.campaign-archive.com",
    "lang": "en",
    "scope": "World",
    "isDarkLogo": false,
    "originalRssUrl": "https://us14.campaign-archive.com/feed?u=5c5e54d49b987a66678f4182c&id=2769f0ee4a"
  },
  {
    "title": "October 2025 Newsletter | Knowledge Rights 21",
    "link": "https://mailchi.mp/knowledgerights21/oct-2025-kr21-newsletter",
    "pubDate": "2025-11-03T13:00:00.000Z",
    "content": "<!----><!--[if !gte mso 9]><!----><html><head></head><body><span class=\"mcnPreviewText\">New KR21 commissioned e-Lending report by CREATe, upcoming conferences &amp; webinar,  KR21 reflections, community updates, and resources</span><!--<![endif]-->\n<!---->\n<div>͏ ‌ &nbsp;    ͏ ‌ &nbsp;    ͏ ‌ &nbsp;    ͏ ‌ &nbsp;    ͏ ‌ &nbsp;    ͏ ‌ &nbsp;    ͏ ‌ &nbsp;    ͏ ‌ &nbsp;    ͏ ‌ &nbsp;    ͏ ‌ &nbsp;    ͏ ‌ &nbsp;    ͏ ‌ &nbsp;    ͏ ‌ &nbsp;    ͏ ‌ &nbsp;    ͏ ‌ &nbsp;    ͏ ‌ &nbsp;    ͏ ‌ &nbsp;    ...",
    "creator": "",
    "sourceTitle": "Knowledge Rights 21 Archive Feed",
    "sheetCategory": "Digital policy + rights",
    "enforcedImage": "https://mcusercontent.com/5c5e54d49b987a66678f4182c/images/fda108a9-e438-ccce-8b7a-129e694b7392.png",
    "sourceDescription": "",
    "sourceLogo": "https://www.google.com/s2/favicons?sz=128&domain=us14.campaign-archive.com",
    "lang": "en",
    "scope": "World",
    "isDarkLogo": false,
    "originalRssUrl": "https://us14.campaign-archive.com/feed?u=5c5e54d49b987a66678f4182c&id=2769f0ee4a"
  },
  {
    "title": "August-September 2025 Newsletter | Knowledge Rights 21",
    "link": "https://mailchi.mp/knowledgerights21/aug-sept-2025-kr21-newsletter",
    "pubDate": "2025-09-30T12:45:00.000Z",
    "content": "<!----><!--[if !gte mso 9]><!----><html><head></head><body><span class=\"mcnPreviewText\">New KR21 supported Open Science &amp; copyright report, upcoming rights retention &amp; e-Lending webinars, KR21 reflections, community updates, and resources</span><!--<![endif]-->\n<!---->\n<div>͏ ‌ &nbsp;    ͏ ‌ &nbsp;    ͏ ‌ &nbsp;    ͏ ‌ &nbsp;    ͏ ‌ &nbsp;    ͏ ‌ &nbsp;    ͏ ‌ &nbsp;    ͏ ‌ &nbsp;    ͏ ‌ &nbsp;    ͏ ‌ &nbsp;    ͏ ‌ &nbsp;    ͏ ‌ &nbsp;    ͏ ‌ &nbsp;    ͏ ‌ &nbsp;    ͏ ‌ &nbsp;    ͏ ‌ &nb...",
    "creator": "",
    "sourceTitle": "Knowledge Rights 21 Archive Feed",
    "sheetCategory": "Digital policy + rights",
    "enforcedImage": "https://mcusercontent.com/5c5e54d49b987a66678f4182c/images/fda108a9-e438-ccce-8b7a-129e694b7392.png",
    "sourceDescription": "",
    "sourceLogo": "https://www.google.com/s2/favicons?sz=128&domain=us14.campaign-archive.com",
    "lang": "en",
    "scope": "World",
    "isDarkLogo": false,
    "originalRssUrl": "https://us14.campaign-archive.com/feed?u=5c5e54d49b987a66678f4182c&id=2769f0ee4a"
  },
  {
    "title": "July 2025 Newsletter | Knowledge Rights 21",
    "link": "https://mailchi.mp/knowledgerights21/july-2025-kr21-newsletter",
    "pubDate": "2025-07-31T12:30:00.000Z",
    "content": "<!----><html><head></head><body><div>͏ ‌ &nbsp;    ͏ ‌ &nbsp;    ͏ ‌ &nbsp;    ͏ ‌ &nbsp;    ͏ ‌ &nbsp;    ͏ ‌ &nbsp;    ͏ ‌ &nbsp;    ͏ ‌ &nbsp;    ͏ ‌ &nbsp;    ͏ ‌ &nbsp;    ͏ ‌ &nbsp;    ͏ ‌ &nbsp;    ͏ ‌ &nbsp;    ͏ ‌ &nbsp;    ͏ ‌ &nbsp;    ͏ ‌ &nbsp;    ͏ ‌ &nbsp;    ͏ ‌ &nbsp;    ͏ ‌ &nbsp;    ͏ ‌ &nbsp;    ͏ ‌ &nbsp;    ͏ ‌ &nbsp;    ͏ ‌ &nbsp;    ͏ ‌ &nbsp;    ͏ ‌ &nbsp;    ͏ ‌ &nbsp;    ͏ ‌ &nbsp;    ͏ ‌ &nbsp;    ͏ ‌ &nbsp;    ͏ ‌ &nbsp;    ͏ ‌ &nbsp;    ͏ ‌ &nbsp;    ͏ ‌ &nbsp;    ͏...",
    "creator": "",
    "sourceTitle": "Knowledge Rights 21 Archive Feed",
    "sheetCategory": "Digital policy + rights",
    "enforcedImage": "https://mcusercontent.com/5c5e54d49b987a66678f4182c/images/fda108a9-e438-ccce-8b7a-129e694b7392.png",
    "sourceDescription": "",
    "sourceLogo": "https://www.google.com/s2/favicons?sz=128&domain=us14.campaign-archive.com",
    "lang": "en",
    "scope": "World",
    "isDarkLogo": false,
    "originalRssUrl": "https://us14.campaign-archive.com/feed?u=5c5e54d49b987a66678f4182c&id=2769f0ee4a"
  },
  {
    "title": "March - June 2025 Newsletter | Knowledge Rights 21",
    "link": "https://mailchi.mp/knowledgerights21/march-june-2025-kr21-newsletter",
    "pubDate": "2025-06-25T12:15:00.000Z",
    "content": "<!----><!--[if !gte mso 9]><!----><html><head></head><body><span class=\"mcnPreviewText\">Discover new reports, upcoming events, fresh KR21 insights, must-watch webinar recordings, lots of KR21 community updates, and helpful resources!</span><!--<![endif]-->\n<!---->\n<div>͏ ‌ &nbsp;    ͏ ‌ &nbsp;    ͏ ‌ &nbsp;    ͏ ‌ &nbsp;    ͏ ‌ &nbsp;    ͏ ‌ &nbsp;    ͏ ‌ &nbsp;    ͏ ‌ &nbsp;    ͏ ‌ &nbsp;    ͏ ‌ &nbsp;    ͏ ‌ &nbsp;    ͏ ‌ &nbsp;    ͏ ‌ &nbsp;    ͏ ‌ &nbsp;    ͏ ‌ &nbsp;    ͏ ‌ &nbsp;    ͏ ‌ &n...",
    "creator": "",
    "sourceTitle": "Knowledge Rights 21 Archive Feed",
    "sheetCategory": "Digital policy + rights",
    "enforcedImage": "https://mcusercontent.com/5c5e54d49b987a66678f4182c/images/fda108a9-e438-ccce-8b7a-129e694b7392.png",
    "sourceDescription": "",
    "sourceLogo": "https://www.google.com/s2/favicons?sz=128&domain=us14.campaign-archive.com",
    "lang": "en",
    "scope": "World",
    "isDarkLogo": false,
    "originalRssUrl": "https://us14.campaign-archive.com/feed?u=5c5e54d49b987a66678f4182c&id=2769f0ee4a"
  },
  {
    "title": "Jan-Feb 2025 Newsletter | Knowledge Rights 21",
    "link": "https://mailchi.mp/knowledgerights21/janfeb2025-kr21-newsletter",
    "pubDate": "2025-03-06T10:00:00.000Z",
    "content": "<!----><!--[if !gte mso 9]><!----><html><head></head><body><span class=\"mcnPreviewText\">New reports, upcoming webinars, calls to action, and community highlights from across Europe</span><!--<![endif]-->\n<!---->\n<div>͏ ‌ &nbsp;    ͏ ‌ &nbsp;    ͏ ‌ &nbsp;    ͏ ‌ &nbsp;    ͏ ‌ &nbsp;    ͏ ‌ &nbsp;    ͏ ‌ &nbsp;    ͏ ‌ &nbsp;    ͏ ‌ &nbsp;    ͏ ‌ &nbsp;    ͏ ‌ &nbsp;    ͏ ‌ &nbsp;    ͏ ‌ &nbsp;    ͏ ‌ &nbsp;    ͏ ‌ &nbsp;    ͏ ‌ &nbsp;    ͏ ‌ &nbsp;    ͏ ‌ &nbsp;    ͏ ‌ &nbsp;    ͏ ‌ &nbsp;    ͏ ‌...",
    "creator": "",
    "sourceTitle": "Knowledge Rights 21 Archive Feed",
    "sheetCategory": "Digital policy + rights",
    "enforcedImage": "https://mcusercontent.com/5c5e54d49b987a66678f4182c/images/fda108a9-e438-ccce-8b7a-129e694b7392.png",
    "sourceDescription": "",
    "sourceLogo": "https://www.google.com/s2/favicons?sz=128&domain=us14.campaign-archive.com",
    "lang": "en",
    "scope": "World",
    "isDarkLogo": false,
    "originalRssUrl": "https://us14.campaign-archive.com/feed?u=5c5e54d49b987a66678f4182c&id=2769f0ee4a"
  },
  {
    "title": "Winter 2024 Newsletter | Knowledge Rights 21",
    "link": "https://mailchi.mp/knowledgerights21/winter2024-kr21-newsletter",
    "pubDate": "2024-12-19T10:30:00.000Z",
    "content": "<!----><!--[if !gte mso 9]><!----><html><head></head><body><span class=\"mcnPreviewText\">KR21's 5-year extension, updates on TPM and eLending research &amp; community highlights from across Europe. Join the Rights Retention movement in 2025!</span><!--<![endif]-->\n<!---->\n<center>\n<table border=\"0\" cellpadding=\"0\" cellspacing=\"0\" height=\"100%\" width=\"100%\" id=\"bodyTable\">\n<tbody><tr>\n<td class=\"bodyCell\" align=\"center\" valign=\"top\">\n<table id=\"root\" border=\"0\" cellpadding=\"0\" cellspacing=\"0\" widt...",
    "creator": "",
    "sourceTitle": "Knowledge Rights 21 Archive Feed",
    "sheetCategory": "Digital policy + rights",
    "enforcedImage": "https://mcusercontent.com/5c5e54d49b987a66678f4182c/images/fda108a9-e438-ccce-8b7a-129e694b7392.png",
    "sourceDescription": "",
    "sourceLogo": "https://www.google.com/s2/favicons?sz=128&domain=us14.campaign-archive.com",
    "lang": "en",
    "scope": "World",
    "isDarkLogo": false,
    "originalRssUrl": "https://us14.campaign-archive.com/feed?u=5c5e54d49b987a66678f4182c&id=2769f0ee4a"
  },
  {
    "title": "Fall 2024 Newsletter | Knowledge Rights 21",
    "link": "https://mailchi.mp/knowledgerights21/fall2024-kr21-newsletter",
    "pubDate": "2024-11-20T11:30:00.000Z",
    "content": "<!----><!--[if !gte mso 9]><!----><html><head></head><body><span class=\"mcnPreviewText\">Upcoming 21 &amp; 26 November webinars, #RetainYourRights resources, reflections on the new political term, and much more.</span><!--<![endif]-->\n<!---->\n<center>\n<table border=\"0\" cellpadding=\"0\" cellspacing=\"0\" height=\"100%\" width=\"100%\" id=\"bodyTable\">\n<tbody><tr>\n<td class=\"bodyCell\" align=\"center\" valign=\"top\">\n<table id=\"root\" border=\"0\" cellpadding=\"0\" cellspacing=\"0\" width=\"100%\"><tbody data-block-id=...",
    "creator": "",
    "sourceTitle": "Knowledge Rights 21 Archive Feed",
    "sheetCategory": "Digital policy + rights",
    "enforcedImage": "https://mcusercontent.com/5c5e54d49b987a66678f4182c/images/fda108a9-e438-ccce-8b7a-129e694b7392.png",
    "sourceDescription": "",
    "sourceLogo": "https://www.google.com/s2/favicons?sz=128&domain=us14.campaign-archive.com",
    "lang": "en",
    "scope": "World",
    "isDarkLogo": false,
    "originalRssUrl": "https://us14.campaign-archive.com/feed?u=5c5e54d49b987a66678f4182c&id=2769f0ee4a"
  }
]