[
  {
    "title": "Museoiden yritysyhteistyö: uudet mahdollisuudet",
    "link": "https://museoliitto.fi/museoiden-yritysyhteistyo-uudet-mahdollisuudet/",
    "pubDate": "2026-01-13T08:30:48.000Z",
    "content": "The post Museoiden yritysyhteistyö: uudet mahdollisuudet appeared first on Museoliitto.",
    "creator": "Miisa Pulkkinen",
    "sourceTitle": "Museoliitto",
    "sheetCategory": "Kulttuuri + kulttuuriperintö",
    "enforcedImage": null,
    "sourceDescription": "",
    "sourceLogo": "https://museoliitto.fi/wp-content/uploads/2023/06/cropped-favicon-32x32.png"
  },
  {
    "title": "Museopäivien 2026 puhujat",
    "link": "https://museoliitto.fi/museopaivien-2026-puhujat/",
    "pubDate": "2025-12-23T08:57:13.000Z",
    "content": "The post Museopäivien 2026 puhujat appeared first on Museoliitto.",
    "creator": "Kirsti Ruissalo",
    "sourceTitle": "Museoliitto",
    "sheetCategory": "Kulttuuri + kulttuuriperintö",
    "enforcedImage": "https://museoliitto.fi/wp-content/uploads/2025/12/museopauvat-2026_puhujaesittely_koivula.png",
    "sourceDescription": "",
    "sourceLogo": "https://museoliitto.fi/wp-content/uploads/2023/06/cropped-favicon-32x32.png"
  },
  {
    "title": "Museopäivien ohjelma 2026: Perjantai 22.5.2026",
    "link": "https://museoliitto.fi/museopaivien-ohjelma-2026-perjantai-22-5-2026/",
    "pubDate": "2025-12-16T08:03:34.000Z",
    "content": "The post Museopäivien ohjelma 2026: Perjantai 22.5.2026 appeared first on Museoliitto.",
    "creator": "Kirsti Ruissalo",
    "sourceTitle": "Museoliitto",
    "sheetCategory": "Kulttuuri + kulttuuriperintö",
    "enforcedImage": null,
    "sourceDescription": "",
    "sourceLogo": "https://museoliitto.fi/wp-content/uploads/2023/06/cropped-favicon-32x32.png"
  },
  {
    "title": "Museopäivät 2026: Torstai 21.5.2026",
    "link": "https://museoliitto.fi/museopaivat-2026-torstai-21-5-2026/",
    "pubDate": "2025-12-16T07:55:28.000Z",
    "content": "The post Museopäivät 2026: Torstai 21.5.2026 appeared first on Museoliitto.",
    "creator": "Kirsti Ruissalo",
    "sourceTitle": "Museoliitto",
    "sheetCategory": "Kulttuuri + kulttuuriperintö",
    "enforcedImage": null,
    "sourceDescription": "",
    "sourceLogo": "https://museoliitto.fi/wp-content/uploads/2023/06/cropped-favicon-32x32.png"
  },
  {
    "title": "Museopäivät 2026 ohjelma: Keskiviikko 20.5.2026",
    "link": "https://museoliitto.fi/museopaivat-2026-ohjelma-keskiviikko-20-5-2026/",
    "pubDate": "2025-12-16T07:45:13.000Z",
    "content": "The post Museopäivät 2026 ohjelma: Keskiviikko 20.5.2026 appeared first on Museoliitto.",
    "creator": "Kirsti Ruissalo",
    "sourceTitle": "Museoliitto",
    "sheetCategory": "Kulttuuri + kulttuuriperintö",
    "enforcedImage": null,
    "sourceDescription": "",
    "sourceLogo": "https://museoliitto.fi/wp-content/uploads/2023/06/cropped-favicon-32x32.png"
  },
  {
    "title": "Talouden ja kannattavuuden kehittäminen museoalalla kevät 2026",
    "link": "https://museoliitto.fi/talouden-ja-kannattavuuden-kehittaminen-museoalalla-kevat-2026/",
    "pubDate": "2025-11-14T10:19:30.000Z",
    "content": "The post Talouden ja kannattavuuden kehittäminen museoalalla kevät 2026 appeared first on Museoliitto.",
    "creator": "Kirsti Ruissalo",
    "sourceTitle": "Museoliitto",
    "sheetCategory": "Kulttuuri + kulttuuriperintö",
    "enforcedImage": null,
    "sourceDescription": "",
    "sourceLogo": "https://museoliitto.fi/wp-content/uploads/2023/06/cropped-favicon-32x32.png"
  },
  {
    "title": "Työyhteisökulttuurin kehittäminen museoalalla kevät 2026",
    "link": "https://museoliitto.fi/tyoyhteisokulttuurin-kehittaminen-museoalalla-kevat-2026/",
    "pubDate": "2025-11-10T07:59:57.000Z",
    "content": "The post Työyhteisökulttuurin kehittäminen museoalalla kevät 2026 appeared first on Museoliitto.",
    "creator": "Kirsti Ruissalo",
    "sourceTitle": "Museoliitto",
    "sheetCategory": "Kulttuuri + kulttuuriperintö",
    "enforcedImage": null,
    "sourceDescription": "",
    "sourceLogo": "https://museoliitto.fi/wp-content/uploads/2023/06/cropped-favicon-32x32.png"
  },
  {
    "title": "Nimitysvaliokunta",
    "link": "https://museoliitto.fi/nimitysvaliokunta/",
    "pubDate": "2025-10-28T11:21:51.000Z",
    "content": "The post Nimitysvaliokunta appeared first on Museoliitto.",
    "creator": "Miisa Pulkkinen",
    "sourceTitle": "Museoliitto",
    "sheetCategory": "Kulttuuri + kulttuuriperintö",
    "enforcedImage": null,
    "sourceDescription": "",
    "sourceLogo": "https://museoliitto.fi/wp-content/uploads/2023/06/cropped-favicon-32x32.png"
  },
  {
    "title": "Museopäivät 2026: Majoitustarjoukset",
    "link": "https://museoliitto.fi/museopaivat-2026-majoitustarjoukset/",
    "pubDate": "2025-10-13T11:33:59.000Z",
    "content": "The post Museopäivät 2026: Majoitustarjoukset appeared first on Museoliitto.",
    "creator": "Kirsti Ruissalo",
    "sourceTitle": "Museoliitto",
    "sheetCategory": "Kulttuuri + kulttuuriperintö",
    "enforcedImage": null,
    "sourceDescription": "",
    "sourceLogo": "https://museoliitto.fi/wp-content/uploads/2023/06/cropped-favicon-32x32.png"
  },
  {
    "title": "Etkot",
    "link": "https://museoliitto.fi/etkot/",
    "pubDate": "2025-05-08T05:50:45.000Z",
    "content": "The post Etkot appeared first on Museoliitto.",
    "creator": "Emilia Merisalo",
    "sourceTitle": "Museoliitto",
    "sheetCategory": "Kulttuuri + kulttuuriperintö",
    "enforcedImage": null,
    "sourceDescription": "",
    "sourceLogo": "https://museoliitto.fi/wp-content/uploads/2023/06/cropped-favicon-32x32.png"
  }
]