[
  {
    "title": "Vuoden 2025 Lumilapio-finalistit on julkaistu",
    "link": "https://www.tutkiva.fi/vuoden-2025-lumilapio-finalistit-on-julkaistu/",
    "pubDate": "2026-04-20T13:43:56.000Z",
    "content": "<html><head></head><body><p>Tutkivan journalismin yhdistys on valinnut vuoden 2025 Lumilapio-palkinnon ehdokkaat. Ehdolla maan parhaaksi tutkivaksi jutuksi on kuusi juttukokonaisuutta valtakunnallisessa kategoriassa ja kolme paikallis-alueellisessa kategoriassa.</p>\n\n\n\n<p>Tänä vuonna useammassa ehdokaslistan juttukokonaisuudessa on hyödynnetty kansainvälistä yhteistyötä. Yhdistys on ilahtunut siitä, että suomalaiset toimitukset ovat löytäneet rajat ylittäviä verkostoja, joiden avulla voidaan tutkia kansainvälisiä ilmiöitä.&nbsp;</p>\n\n\n\n<p>”Kansainvälinen yhteistyö ei ole enää lisäarvo vaan välttämättömyys. Järjestäytynyt rikollisuus ja talouden hämärät virrat eivät pysähdy Suomen rajoille, eivätkä ne pysähdy Euroopankaan rajoille. Suomalaiset toimittajat ovat yhä useammin osa eurooppalaisia ja maailmanlaajuisia verkostoja, joissa toimittaja auttaa toimittajaa yli rajojen”, kuvailee Tutkivan journalismin yhdistyksen puheenjohtaja Olli Pietiläinen.</p>\n\n\n\n<p>Ehdokaslistassa on niin ikään juttukokonaisuuksia, joissa on hyödynnetty tekoälyä.</p>\n\n\n\n<p>”Tekoälyn käyttö tutkivassa journalismissa vaatii erityistä huolellisuutta. On ilahduttavaa nähdä, että toimitukset ovat lähestyneet metodeja harkiten ja käsitel</p></body></html>",
    "snippet": "Tutkivan journalismin yhdistys on valinnut vuoden 2025 Lumilapio-palkinnon ehdokkaat. Ehdolla maan parhaaksi tutkivaksi jutuksi on kuusi juttukokonaisuutta valtakunnallisessa kategoriassa ja kolme pai",
    "creator": "Tutkiva hallitus",
    "sourceTitle": "Tutkivan journalismin yhdistys –tutkiva.fi",
    "sheetCategory": "Investigations + Conflict",
    "enforcedImage": null,
    "sourceDescription": "",
    "sourceLogo": "https://www.tutkiva.fi/wp-content/uploads/2017/05/cropped-TUTKIVA01-32x32.png",
    "lang": "fi",
    "scope": "World",
    "isDarkLogo": false,
    "originalRssUrl": "https://www.tutkiva.fi/feed/"
  }
]