[
  {
    "title": "Klaus Hedman awarded with the Pekka Halonen medal",
    "link": "https://www.helsinki.fi/en/researchgroups/virus-infections-and-immunity/our-latest-news/klaus-hedman-awarded-with-the-pekka-halonen-medal",
    "pubDate": "2026-04-09T14:05:31.000Z",
    "content": "<html><head></head><body><div class=\"hy-main-content-wrapper\">\n        <div class=\"page-title__wrapper page-title__wrapper--common\">\n          <h1 class=\"page-title__h1 page-title__h1--common\">\n            Klaus Hedman awarded with the Pekka Halonen medal\n          </h1>\n        </div>\n      </div>\n      <span><span>maperdom@helsinki.fi</span></span>\n<span><time datetime=\"2026-04-09T17:05:31+03:00\" title=\"Thursday, April 9, 2026 - 17:05\">Thu, 09/04/2026 - 17:05</time>\n</span>\n\n                    \n\n\n  <div class=\"paragraph paragraph--type--text-paragraph paragraph--view-mode--default\">\n    \n              <div class=\"hy-main-content-wrapper\">\n                \t          <hy-heading heading=\"h2\" id=\"celebrating-klaus’s-lifetime-achievements\" section=\"\">\n            Celebrating Klaus’s Lifetime Achievements\n          </hy-heading>\n              \n      <hy-paragraph-text variant=\"placement=external\">\n        \n                    <p>At the opening of the Finnish Virology Days held on March 20–21, 2026, Klaus Hedman was awarded the <strong>Pekka Halonen Medal</strong> in recognition of his lifetime contributions to clinical virology.</p>\n<p>His decades-long career has had a profound impact on both research and cl</p></hy-paragraph-text></div></div></body></html>",
    "snippet": "Klaus Hedman awarded with the Pekka Halonen medal maperdom@helsinki.fi Thu, 09/04/2026 - 17:05 Celebrating Klaus’s Lifetime Achievements At the opening of the Finnish Virology Days held on March 20–21",
    "creator": "maperdom@helsinki.fi",
    "sourceTitle": "University of Helsinki",
    "sheetCategory": "(Open) Science + Research",
    "enforcedImage": null,
    "sourceDescription": "",
    "sourceLogo": "https://www.google.com/s2/favicons?sz=128&domain=www.helsinki.fi",
    "lang": "fi",
    "scope": "Finland",
    "isDarkLogo": false,
    "originalRssUrl": "https://www.helsinki.fi/rss.xml"
  },
  {
    "title": "From Cells to Systems: Advances in High-content imaging and 3D Image Analysis Symposium",
    "link": "https://www.helsinki.fi/en/infrastructures/bioimaging/news-archive/cells-systems-advances-high-content-imaging-and-3d-image-analysis-symposium",
    "pubDate": "2026-04-09T10:23:15.000Z",
    "content": "<html><head></head><body><div class=\"hy-main-content-wrapper\">\n        <div class=\"page-title__wrapper page-title__wrapper--common\">\n          <h1 class=\"page-title__h1 page-title__h1--common\">\n            From Cells to Systems: Advances in High-content imaging and 3D Image Analysis Symposium\n          </h1>\n        </div>\n      </div>\n      <span><span>veikkava@helsinki.fi</span></span>\n<span><time datetime=\"2026-04-09T13:23:15+03:00\" title=\"Thursday, April 9, 2026 - 13:23\">Thu, 09/04/2026 - 13:23</time>\n</span>\n\n                    <div class=\"hy-main-content-wrapper\">\n              <hy-ingress>Date: Tuesday 12. May 2026 <br>\nVenue: Biomedicum 1, University of Helsinki, Helsinki, Finland <br>\nNo registration fee<br>\nRegistration link at the bottom</hy-ingress>\n          </div>\n            \n                    \n\n\n  <div class=\"paragraph paragraph--type--text-paragraph paragraph--view-mode--default\">\n    \n              <div class=\"hy-main-content-wrapper\">\n                \t          <hy-heading heading=\"h2\" id=\"program\" section=\"\">\n            Program\n          </hy-heading>\n              \n      <hy-paragraph-text variant=\"placement=external\">\n        \n                    <p><em>8.30 Registration and coffe</em></p></hy-paragraph-text></div></div></body></html>",
    "snippet": "From Cells to Systems: Advances in High-content imaging and 3D Image Analysis Symposium veikkava@helsinki.fi Thu, 09/04/2026 - 13:23 Date: Tuesday 12. May 2026 Venue: Biomedicum 1, University of Helsi",
    "creator": "veikkava@helsinki.fi",
    "sourceTitle": "University of Helsinki",
    "sheetCategory": "(Open) Science + Research",
    "enforcedImage": null,
    "sourceDescription": "",
    "sourceLogo": "https://www.google.com/s2/favicons?sz=128&domain=www.helsinki.fi",
    "lang": "fi",
    "scope": "Finland",
    "isDarkLogo": false,
    "originalRssUrl": "https://www.helsinki.fi/rss.xml"
  },
  {
    "title": "5th Summer School on Sustainable Pharmacy hosted by University of Helsinki in September 2026",
    "link": "https://www.helsinki.fi/en/faculty-pharmacy/news/5th-summer-school-sustainable-pharmacy-hosted-university-helsinki-september-2026",
    "pubDate": "2026-04-09T07:51:00.000Z",
    "content": "<html><head></head><body><div class=\"hy-main-content-wrapper\">\n        <div class=\"page-title__wrapper page-title__wrapper--common\">\n          <h1 class=\"page-title__h1 page-title__h1--common\">\n            5th Summer School on Sustainable Pharmacy hosted by University of Helsinki in September 2026\n          </h1>\n        </div>\n      </div>\n      <span><span>lindymar@helsinki.fi</span></span>\n<span><time datetime=\"2026-04-09T10:51:00+03:00\" title=\"Thursday, April 9, 2026 - 10:51\">Thu, 09/04/2026 - 10:51</time>\n</span>\n\n                    <div class=\"hy-main-content-wrapper\">\n              <hy-ingress>Faculty of Pharmacy, University of Helsinki, hosts the 5th Summer School on Sustainable Pharmacy on 7–10 September 2026. The event offers a multifaceted view on sustainability in pharmacy for doctoral researchers, students, professionals and stakeholders from Finland and abroad. Registration is free.</hy-ingress>\n          </div>\n            \n                    \n\n\n  <div class=\"paragraph paragraph--type--text-paragraph paragraph--view-mode--default\">\n    \n              <div class=\"hy-main-content-wrapper\">\n              \n      <hy-paragraph-text variant=\"placement=external\">\n        \n                    <p>T</p></hy-paragraph-text></div></div></body></html>",
    "snippet": "5th Summer School on Sustainable Pharmacy hosted by University of Helsinki in September 2026 lindymar@helsinki.fi Thu, 09/04/2026 - 10:51 Faculty of Pharmacy, University of Helsinki, hosts the 5th Sum",
    "creator": "lindymar@helsinki.fi",
    "sourceTitle": "University of Helsinki",
    "sheetCategory": "(Open) Science + Research",
    "enforcedImage": null,
    "sourceDescription": "",
    "sourceLogo": "https://www.google.com/s2/favicons?sz=128&domain=www.helsinki.fi",
    "lang": "fi",
    "scope": "Finland",
    "isDarkLogo": false,
    "originalRssUrl": "https://www.helsinki.fi/rss.xml"
  },
  {
    "title": "Kun tunnen olevani pieni – Näyttely pienuuden voimasta",
    "link": "https://www.helsinki.fi/fi/luomus/tietoa-meista/uutiset/kun-tunnen-olevani-pieni-nayttely-pienuuden-voimasta",
    "pubDate": "2026-04-09T05:31:02.000Z",
    "content": "<html><head></head><body><div class=\"hy-main-content-wrapper\">\n        <div class=\"page-title__wrapper page-title__wrapper--common\">\n          <h1 class=\"page-title__h1 page-title__h1--common\">\n            When I Feel Small – An exhibition on the power of smallness\n          </h1>\n        </div>\n      </div>\n      <span><span>johanemi@helsinki.fi</span></span>\n<span><time datetime=\"2026-04-09T09:31:48+03:00\" title=\"Thursday, April 9, 2026 - 09:31\">Thu, 09/04/2026 - 09:31</time>\n</span>\n\n                    <div class=\"hy-main-content-wrapper\">\n              <hy-ingress>Sarah Guedes’s exhibition is on view at the Gallery Corridor of the Kaisaniemi Greenhouses from 14 April to 14 June 2026.</hy-ingress>\n          </div>\n            \n                    \n\n\n  <div class=\"paragraph paragraph--type--text-paragraph paragraph--view-mode--default\">\n    \n              <div class=\"hy-main-content-wrapper\">\n              \n      <hy-paragraph-text variant=\"placement=external\">\n        \n                    <p dir=\"ltr\"><em>When I Feel Small</em> is the debut solo exhibition of Brazilian artist <strong>Sarah Guedes</strong>, presenting a collection of colored-pencil illustrations rooted in a simple question: what do we d</p></hy-paragraph-text></div></div></body></html>",
    "snippet": "When I Feel Small – An exhibition on the power of smallness johanemi@helsinki.fi Thu, 09/04/2026 - 09:31 Sarah Guedes’s exhibition is on view at the Gallery Corridor of the Kaisaniemi Greenhouses from",
    "creator": "johanemi@helsinki.fi",
    "sourceTitle": "University of Helsinki",
    "sheetCategory": "(Open) Science + Research",
    "enforcedImage": null,
    "sourceDescription": "",
    "sourceLogo": "https://www.google.com/s2/favicons?sz=128&domain=www.helsinki.fi",
    "lang": "fi",
    "scope": "Finland",
    "isDarkLogo": false,
    "originalRssUrl": "https://www.helsinki.fi/rss.xml"
  },
  {
    "title": "Seminar on Normativity - Seminaari normatiivisuudesta",
    "link": "https://www.helsinki.fi/en/researchgroups/meliorist-philosophy-of-suffering/news/seminar-on-normativity-seminaari-normatiivisuudesta",
    "pubDate": "2026-04-08T12:03:36.000Z",
    "content": "<html><head></head><body><div class=\"hy-main-content-wrapper\">\n        <div class=\"page-title__wrapper page-title__wrapper--common\">\n          <h1 class=\"page-title__h1 page-title__h1--common\">\n            Seminar on Normativity - Seminaari normatiivisuudesta\n          </h1>\n        </div>\n      </div>\n      <span><span>tauranne@helsinki.fi</span></span>\n<span><time datetime=\"2026-04-08T15:03:36+03:00\" title=\"Wednesday, April 8, 2026 - 15:03\">Wed, 08/04/2026 - 15:03</time>\n</span>\n\n                    <div class=\"hy-main-content-wrapper\">\n              <hy-ingress>A seminar discussing norms and normativity will be organized in Finnish on May 7, 2026.</hy-ingress>\n          </div>\n            \n                    \n\n\n  <div class=\"paragraph paragraph--type--text-paragraph paragraph--view-mode--default\">\n    \n              <div class=\"hy-main-content-wrapper\">\n              \n      <hy-paragraph-text variant=\"placement=external\">\n        \n                    <p>Inhimillistä elämää määrittää normatiivisuus. Normeihin kohdistuu ajassamme yleistä epävarmuutta. Rapautuvatko sääntöpohjaisen järjestyksen, kansainvälisen oikeuden ja sopimusten, perustuslain sekä tiedonhankinnan ja totuuden tavoittelun normit? Seminaa</p></hy-paragraph-text></div></div></body></html>",
    "snippet": "Seminar on Normativity - Seminaari normatiivisuudesta tauranne@helsinki.fi Wed, 08/04/2026 - 15:03 A seminar discussing norms and normativity will be organized in Finnish on May 7, 2026. Inhimillistä ",
    "creator": "tauranne@helsinki.fi",
    "sourceTitle": "University of Helsinki",
    "sheetCategory": "(Open) Science + Research",
    "enforcedImage": null,
    "sourceDescription": "",
    "sourceLogo": "https://www.google.com/s2/favicons?sz=128&domain=www.helsinki.fi",
    "lang": "fi",
    "scope": "Finland",
    "isDarkLogo": false,
    "originalRssUrl": "https://www.helsinki.fi/rss.xml"
  },
  {
    "title": "Societal impact of linguistic research",
    "link": "https://www.helsinki.fi/en/researchgroups/comparing-and-contrasting-languages-and-cultures/news-events/societal-impact-of-linguistic-research",
    "pubDate": "2026-04-08T11:24:42.000Z",
    "content": "<html><head></head><body><div class=\"hy-main-content-wrapper\">\n        <div class=\"page-title__wrapper page-title__wrapper--common\">\n          <h1 class=\"page-title__h1 page-title__h1--common\">\n            Societal impact of linguistic research\n          </h1>\n        </div>\n      </div>\n      <span><span>cruscsi@helsinki.fi</span></span>\n<span><time datetime=\"2026-04-08T14:24:42+03:00\" title=\"Wednesday, April 8, 2026 - 14:24\">Wed, 08/04/2026 - 14:24</time>\n</span>\n\n                    <div class=\"hy-main-content-wrapper\">\n              <hy-ingress>2 June 2 2026, University of Helsinki, Main building. <br>\nInvited speaker: Dr. Josep Cru (Newcastle University, Linguapax).<br>\nOrganizers: Roosa Pöllänen, Héloïse Calame, Eeva Sippola &amp; Friederike Lüpke.</hy-ingress>\n          </div>\n            \n                    \n\n\n  <div class=\"paragraph paragraph--type--text-paragraph paragraph--view-mode--default\">\n    \n              <div class=\"hy-main-content-wrapper\">\n                \t          <hy-heading heading=\"h2\" id=\"description-of-the-workshop:\" section=\"\">\n            Description of the workshop:\n          </hy-heading>\n              \n      <hy-paragraph-text variant=\"placement=external\">\n        \n       </hy-paragraph-text></div></div></body></html>",
    "snippet": "Societal impact of linguistic research cruscsi@helsinki.fi Wed, 08/04/2026 - 14:24 2 June 2 2026, University of Helsinki, Main building. Invited speaker: Dr. Josep Cru (Newcastle University, Linguapax",
    "creator": "cruscsi@helsinki.fi",
    "sourceTitle": "University of Helsinki",
    "sheetCategory": "(Open) Science + Research",
    "enforcedImage": null,
    "sourceDescription": "",
    "sourceLogo": "https://www.google.com/s2/favicons?sz=128&domain=www.helsinki.fi",
    "lang": "fi",
    "scope": "Finland",
    "isDarkLogo": false,
    "originalRssUrl": "https://www.helsinki.fi/rss.xml"
  },
  {
    "title": "MultiBEING Justice Centre of Excellence Kick-off",
    "link": "https://www.helsinki.fi/en/researchgroups/indigenous-studies/news-events/multibeing-justice-centre-of-excellence-kick-off",
    "pubDate": "2026-04-08T11:01:48.000Z",
    "content": "<html><head></head><body><div class=\"hy-main-content-wrapper\">\n        <div class=\"page-title__wrapper page-title__wrapper--common\">\n          <h1 class=\"page-title__h1 page-title__h1--common\">\n            MultiBEING Justice Centre of Excellence Kick-off\n          </h1>\n        </div>\n      </div>\n      <span><span>mfrost@helsinki.fi</span></span>\n<span><time datetime=\"2026-04-08T14:01:48+03:00\" title=\"Wednesday, April 8, 2026 - 14:01\">Wed, 08/04/2026 - 14:01</time>\n</span>\n\n                    <div class=\"hy-main-content-wrapper\">\n              <hy-ingress>Last week on Monday March 30th, the MultiBEING Justice Centre of Excellence team had a successful kick-off in Aanaar (Inari). At the opening event, researchers presented and discussed their forthcoming research in Sámi home region.  <br>\n<br>\n </hy-ingress>\n          </div>\n            \n                    \n\n\n  <div class=\"paragraph paragraph--type--text-paragraph paragraph--view-mode--default\">\n    \n              <div class=\"hy-main-content-wrapper\">\n              \n      <hy-paragraph-text variant=\"placement=external\">\n        \n                    <p>Last week on Monday March 30<sup>th</sup>, the MultiBEING Justice Centre of Excellence (CoE) team had a</p></hy-paragraph-text></div></div></body></html>",
    "snippet": "MultiBEING Justice Centre of Excellence Kick-off mfrost@helsinki.fi Wed, 08/04/2026 - 14:01 Last week on Monday March 30th, the MultiBEING Justice Centre of Excellence team had a successful kick-off i",
    "creator": "mfrost@helsinki.fi",
    "sourceTitle": "University of Helsinki",
    "sheetCategory": "(Open) Science + Research",
    "enforcedImage": null,
    "sourceDescription": "",
    "sourceLogo": "https://www.google.com/s2/favicons?sz=128&domain=www.helsinki.fi",
    "lang": "fi",
    "scope": "Finland",
    "isDarkLogo": false,
    "originalRssUrl": "https://www.helsinki.fi/rss.xml"
  },
  {
    "title": "Varhaisempi ADHD-diagnoosi on yhteydessä parempaan koulutukseen",
    "link": "https://www.helsinki.fi/fi/uutiset/yhteiskunta-ja-oppiminen/varhaisempi-adhd-diagnoosi-yhteydessa-parempaan-koulutukseen",
    "pubDate": "2026-04-08T08:50:05.000Z",
    "content": "<html><head></head><body><div class=\"hy-main-content-wrapper\">\n        <div class=\"page-title__wrapper page-title__wrapper--common\">\n          <h1 class=\"page-title__h1 page-title__h1--common\">\n            Earlier ADHD diagnosis linked to better education\n          </h1>\n        </div>\n      </div>\n      <span><span>pakomula@helsinki.fi</span></span>\n<span><time datetime=\"2026-04-09T13:58:24+03:00\" title=\"Thursday, April 9, 2026 - 13:58\">Thu, 09/04/2026 - 13:58</time>\n</span>\n\n                    <div class=\"hy-main-content-wrapper\">\n              <hy-ingress>A new study from the University of Helsinki reveals that receiving an ADHD diagnosis earlier rather than later is associated with better academic performance and lower school dropout rates.</hy-ingress>\n          </div>\n            \n                    \n\n\n  <div class=\"paragraph paragraph--type--text-paragraph paragraph--view-mode--default\">\n    \n              <div class=\"hy-main-content-wrapper\">\n              \n      <hy-paragraph-text variant=\"placement=external\">\n        \n                    <p>Young people diagnosed earlier with ADHD had a higher grade point average at age 16, were more likely to pursue academic degrees, and had a lower likelihood</p></hy-paragraph-text></div></div></body></html>",
    "snippet": "Earlier ADHD diagnosis linked to better education pakomula@helsinki.fi Thu, 09/04/2026 - 13:58 A new study from the University of Helsinki reveals that receiving an ADHD diagnosis earlier rather than ",
    "creator": "pakomula@helsinki.fi",
    "sourceTitle": "University of Helsinki",
    "sheetCategory": "(Open) Science + Research",
    "enforcedImage": null,
    "sourceDescription": "",
    "sourceLogo": "https://www.google.com/s2/favicons?sz=128&domain=www.helsinki.fi",
    "lang": "fi",
    "scope": "Finland",
    "isDarkLogo": false,
    "originalRssUrl": "https://www.helsinki.fi/rss.xml"
  },
  {
    "title": "Arkadiankadun siltaremontti aiheuttaa muutoksia liikennejärjestelyihin Luonnontieteellisen museon lähistöllä",
    "link": "https://www.helsinki.fi/fi/luomus/tietoa-meista/uutiset/arkadiankadun-siltaremontti-aiheuttaa-muutoksia-liikennejarjestelyihin-luonnontieteellisen-museon-lahistolla",
    "pubDate": "2026-01-07T06:13:58.000Z",
    "content": "<html><head></head><body><div class=\"hy-main-content-wrapper\">\n        <div class=\"page-title__wrapper page-title__wrapper--common\">\n          <h1 class=\"page-title__h1 page-title__h1--common\">\n            Renewal of Arkadiankatu Bridge will cause changes to traffic arrangements near the Natural History Museum\n          </h1>\n        </div>\n      </div>\n      <span><span>johanemi@helsinki.fi</span></span>\n<span><time datetime=\"2026-01-07T08:40:18+02:00\" title=\"Wednesday, January 7, 2026 - 08:40\">Wed, 07/01/2026 - 08:40</time>\n</span>\n\n                    <div class=\"hy-main-content-wrapper\">\n              <hy-ingress>The renovation is expected to be completed in late 2026.</hy-ingress>\n          </div>\n            \n                    \n\n\n  <div class=\"paragraph paragraph--type--text-paragraph paragraph--view-mode--default\">\n    \n              <div class=\"hy-main-content-wrapper\">\n              \n      <hy-paragraph-text variant=\"placement=external\">\n        \n                    <p>The renovation will start with the construction of temporary traffic arrangements from Wednesday 7 January onwards. The renovation is expected to be completed in late 2026.</p>\n<p></p></hy-paragraph-text></div></div></body></html>",
    "snippet": "Renewal of Arkadiankatu Bridge will cause changes to traffic arrangements near the Natural History Museum johanemi@helsinki.fi Wed, 07/01/2026 - 08:40 The renovation is expected to be completed in lat",
    "creator": "johanemi@helsinki.fi",
    "sourceTitle": "University of Helsinki",
    "sheetCategory": "(Open) Science + Research",
    "enforcedImage": null,
    "sourceDescription": "",
    "sourceLogo": "https://www.google.com/s2/favicons?sz=128&domain=www.helsinki.fi",
    "lang": "fi",
    "scope": "Finland",
    "isDarkLogo": false,
    "originalRssUrl": "https://www.helsinki.fi/rss.xml"
  },
  {
    "title": "Ukrainan sota - yliopiston suositukset",
    "link": "https://www.helsinki.fi/fi/ajankohtaista/ukrainan-sota",
    "pubDate": "2022-03-04T10:06:50.000Z",
    "content": "<html><head></head><body><div class=\"hy-main-content-wrapper\">\n        <div class=\"page-title__wrapper page-title__wrapper--common\">\n          <h1 class=\"page-title__h1 page-title__h1--common\">\n            The War in Ukraine – University of Helsinki guidelines\n          </h1>\n        </div>\n      </div>\n      <span><span>terojuut@helsinki.fi</span></span>\n<span><time datetime=\"2022-03-04T14:11:21+02:00\" title=\"Friday, March 4, 2022 - 14:11\">Fri, 04/03/2022 - 14:11</time>\n</span>\n\n                    <div class=\"hy-main-content-wrapper\">\n              <hy-ingress>This page contains up-to-date information on the effects of the war in Ukraine on the University of Helsinki as well as University-level recommendations and instructions regarding the situation.</hy-ingress>\n          </div>\n            \n                    \n      <div class=\"hy-main-content-wrapper\">\n          <hy-anchor-link-list list-title=\"Contents of this page\" open-label=\"Open\" close-label=\"Close\" anchor-items=\"\">\n        </hy-anchor-link-list>\n      </div>\n  \n                        \n          <div class=\"hy-main-content-wrapper\">\n          </div></body></html>",
    "snippet": "The War in Ukraine – University of Helsinki guidelines terojuut@helsinki.fi Fri, 04/03/2022 - 14:11 This page contains up-to-date information on the effects of the war in Ukraine on the University of ",
    "creator": "terojuut@helsinki.fi",
    "sourceTitle": "University of Helsinki",
    "sheetCategory": "(Open) Science + Research",
    "enforcedImage": null,
    "sourceDescription": "",
    "sourceLogo": "https://www.google.com/s2/favicons?sz=128&domain=www.helsinki.fi",
    "lang": "fi",
    "scope": "Finland",
    "isDarkLogo": false,
    "originalRssUrl": "https://www.helsinki.fi/rss.xml"
  },
  {
    "title": "Helsingin yliopiston Porthania peruskorjataan",
    "link": "https://www.helsinki.fi/fi/uutiset/yliopistoyhteiso/helsingin-yliopiston-porthania-peruskorjataan",
    "pubDate": "2026-04-09T09:31:00.000Z",
    "content": "<html><head></head><body><div class=\"hy-main-content-wrapper\">\n        <div class=\"page-title__wrapper page-title__wrapper--common\">\n          <h1 class=\"page-title__h1 page-title__h1--common\">\n            University of Helsinki to renovate its Porthania building\n          </h1>\n        </div>\n      </div>\n      <span><span>pettergr@helsinki.fi</span></span>\n<span><time datetime=\"2026-04-10T09:23:50+03:00\" title=\"Friday, April 10, 2026 - 09:23\">Fri, 10/04/2026 - 09:23</time>\n</span>\n\n                    <div class=\"hy-main-content-wrapper\">\n              <hy-ingress>Helsinki University Properties Ltd has decided to invest in an extensive renovation of Porthania.</hy-ingress>\n          </div>\n            \n                    \n\n\n  <div class=\"paragraph paragraph--type--text-paragraph paragraph--view-mode--default\">\n    \n              <div class=\"hy-main-content-wrapper\">\n              \n      <hy-paragraph-text variant=\"placement=external\">\n        \n                    <p>Completed in 1957, the building is a central part of the University of Helsinki’s City Centre Campus and a significant representative of Finnish modern architecture. The renovation will ensure that the building will serve teaching, research </p></hy-paragraph-text></div></div></body></html>",
    "snippet": "University of Helsinki to renovate its Porthania building pettergr@helsinki.fi Fri, 10/04/2026 - 09:23 Helsinki University Properties Ltd has decided to invest in an extensive renovation of Porthania.",
    "creator": "pettergr@helsinki.fi",
    "sourceTitle": "University of Helsinki",
    "sheetCategory": "(Open) Science + Research",
    "enforcedImage": null,
    "sourceDescription": "",
    "sourceLogo": "https://www.google.com/s2/favicons?sz=128&domain=www.helsinki.fi",
    "lang": "fi",
    "scope": "Finland",
    "isDarkLogo": false,
    "originalRssUrl": "https://www.helsinki.fi/rss.xml"
  }
]