[
  {
    "title": "Kiinan Xi vierailee Pohjois-Koreassa",
    "link": "https://yle.fi/a/74-20229932?origin=rss",
    "pubDate": "2026-06-05T03:31:40.000Z",
    "content": "<html><head></head><body></body></html>",
    "snippet": "",
    "creator": "",
    "sourceTitle": "Yle | Kansainvälinen politiikka",
    "sheetCategory": "Politics + Public sector",
    "enforcedImage": null,
    "sourceDescription": "Ylen uutiset aiheesta ”Kansainvälinen politiikka” nopeasti ja luotettavasti.",
    "sourceLogo": "https://www.google.com/s2/favicons?sz=128&domain=yle.fi",
    "lang": "fi",
    "scope": "World",
    "isDarkLogo": false,
    "originalRssUrl": "https://yle.fi/rss/t/18-213332/fi"
  },
  {
    "title": "EU-maiden terveysministerit ylimääräiseen virtuaalikokoukseen ebolaepidemian vuoksi",
    "link": "https://yle.fi/a/74-20229927?origin=rss",
    "pubDate": "2026-06-05T00:29:15.000Z",
    "content": "<html><head></head><body></body></html>",
    "snippet": "",
    "creator": "",
    "sourceTitle": "Yle | Kansainvälinen politiikka",
    "sheetCategory": "Politics + Public sector",
    "enforcedImage": null,
    "sourceDescription": "Ylen uutiset aiheesta ”Kansainvälinen politiikka” nopeasti ja luotettavasti.",
    "sourceLogo": "https://www.google.com/s2/favicons?sz=128&domain=yle.fi",
    "lang": "fi",
    "scope": "World",
    "isDarkLogo": false,
    "originalRssUrl": "https://yle.fi/rss/t/18-213332/fi"
  },
  {
    "title": "Politicon lähteet: Yhdysvallat perumassa Tomahawk-kaupat Saksan kanssa",
    "link": "https://yle.fi/a/74-20229923?origin=rss",
    "pubDate": "2026-06-04T20:38:18.000Z",
    "content": "Politicon virkamieslähteet Yhdysvalloissa ja Euroopassa sanovat, että ohjuskauppojen pelätään suututtavan Venäjän.",
    "snippet": "Politicon virkamieslähteet Yhdysvalloissa ja Euroopassa sanovat, että ohjuskauppojen pelätään suututtavan Venäjän.",
    "creator": "",
    "sourceTitle": "Yle | Kansainvälinen politiikka",
    "sheetCategory": "Politics + Public sector",
    "enforcedImage": null,
    "sourceDescription": "Ylen uutiset aiheesta ”Kansainvälinen politiikka” nopeasti ja luotettavasti.",
    "sourceLogo": "https://www.google.com/s2/favicons?sz=128&domain=yle.fi",
    "lang": "fi",
    "scope": "World",
    "isDarkLogo": false,
    "originalRssUrl": "https://yle.fi/rss/t/18-213332/fi"
  },
  {
    "title": "Rantanen: Suomi selvittää palautuskeskuksen perustamista yhdessä muiden Pohjoismaiden kanssa",
    "link": "https://yle.fi/a/74-20229909?origin=rss",
    "pubDate": "2026-06-04T16:36:32.000Z",
    "content": "Sisäministerin mielestä kuluva viikko on EU:lle suorastaan historiallinen palautusasiassa saavutetun sovun vuoksi.",
    "snippet": "Sisäministerin mielestä kuluva viikko on EU:lle suorastaan historiallinen palautusasiassa saavutetun sovun vuoksi.",
    "creator": "",
    "sourceTitle": "Yle | Kansainvälinen politiikka",
    "sheetCategory": "Politics + Public sector",
    "enforcedImage": null,
    "sourceDescription": "Ylen uutiset aiheesta ”Kansainvälinen politiikka” nopeasti ja luotettavasti.",
    "sourceLogo": "https://www.google.com/s2/favicons?sz=128&domain=yle.fi",
    "lang": "fi",
    "scope": "World",
    "isDarkLogo": false,
    "originalRssUrl": "https://yle.fi/rss/t/18-213332/fi"
  },
  {
    "title": "Romanian presidentti nimitti EU-parlamentaarikko Tomacin pääministeriksi",
    "link": "https://yle.fi/a/74-20229908?origin=rss",
    "pubDate": "2026-06-04T15:45:08.000Z",
    "content": "<html><head></head><body></body></html>",
    "snippet": "",
    "creator": "",
    "sourceTitle": "Yle | Kansainvälinen politiikka",
    "sheetCategory": "Politics + Public sector",
    "enforcedImage": null,
    "sourceDescription": "Ylen uutiset aiheesta ”Kansainvälinen politiikka” nopeasti ja luotettavasti.",
    "sourceLogo": "https://www.google.com/s2/favicons?sz=128&domain=yle.fi",
    "lang": "fi",
    "scope": "World",
    "isDarkLogo": false,
    "originalRssUrl": "https://yle.fi/rss/t/18-213332/fi"
  },
  {
    "title": "Dmitrijev: Venäjä ja Yhdysvallat sopivat Beringinsalmen alittavasta tunnelista",
    "link": "https://yle.fi/a/74-20229892?origin=rss",
    "pubDate": "2026-06-04T14:20:44.000Z",
    "content": "<html><head></head><body></body></html>",
    "snippet": "",
    "creator": "",
    "sourceTitle": "Yle | Kansainvälinen politiikka",
    "sheetCategory": "Politics + Public sector",
    "enforcedImage": null,
    "sourceDescription": "Ylen uutiset aiheesta ”Kansainvälinen politiikka” nopeasti ja luotettavasti.",
    "sourceLogo": "https://www.google.com/s2/favicons?sz=128&domain=yle.fi",
    "lang": "fi",
    "scope": "World",
    "isDarkLogo": false,
    "originalRssUrl": "https://yle.fi/rss/t/18-213332/fi"
  },
  {
    "title": "Norjalainen avustusjärjestö: Sudanissa ja Kongon demokraattisessa tasavallassa kärsitään piilossa maailman katseilta",
    "link": "https://yle.fi/a/74-20229866?origin=rss",
    "pubDate": "2026-06-04T13:23:02.000Z",
    "content": "<html><head></head><body></body></html>",
    "snippet": "",
    "creator": "",
    "sourceTitle": "Yle | Kansainvälinen politiikka",
    "sheetCategory": "Politics + Public sector",
    "enforcedImage": null,
    "sourceDescription": "Ylen uutiset aiheesta ”Kansainvälinen politiikka” nopeasti ja luotettavasti.",
    "sourceLogo": "https://www.google.com/s2/favicons?sz=128&domain=yle.fi",
    "lang": "fi",
    "scope": "World",
    "isDarkLogo": false,
    "originalRssUrl": "https://yle.fi/rss/t/18-213332/fi"
  },
  {
    "title": "Ukrainan EU-jäsenyyspyrkimykset etenemässä Unkarin luovuttua vastustuksesta",
    "link": "https://yle.fi/a/74-20229688?origin=rss",
    "pubDate": "2026-06-03T21:44:44.000Z",
    "content": "<html><head></head><body></body></html>",
    "snippet": "",
    "creator": "",
    "sourceTitle": "Yle | Kansainvälinen politiikka",
    "sheetCategory": "Politics + Public sector",
    "enforcedImage": null,
    "sourceDescription": "Ylen uutiset aiheesta ”Kansainvälinen politiikka” nopeasti ja luotettavasti.",
    "sourceLogo": "https://www.google.com/s2/favicons?sz=128&domain=yle.fi",
    "lang": "fi",
    "scope": "World",
    "isDarkLogo": false,
    "originalRssUrl": "https://yle.fi/rss/t/18-213332/fi"
  },
  {
    "title": "Unkari ja Ukraina pääsivät sopuun Taka-Karpatian vähemmistön asemasta",
    "link": "https://yle.fi/a/74-20229683?origin=rss",
    "pubDate": "2026-06-03T18:33:12.000Z",
    "content": "Unkarin pääministerin mukaan sopu  takaa Unkarin tuen Ukrainan EU-pyrkimyksille.",
    "snippet": "Unkarin pääministerin mukaan sopu takaa Unkarin tuen Ukrainan EU-pyrkimyksille.",
    "creator": "",
    "sourceTitle": "Yle | Kansainvälinen politiikka",
    "sheetCategory": "Politics + Public sector",
    "enforcedImage": null,
    "sourceDescription": "Ylen uutiset aiheesta ”Kansainvälinen politiikka” nopeasti ja luotettavasti.",
    "sourceLogo": "https://www.google.com/s2/favicons?sz=128&domain=yle.fi",
    "lang": "fi",
    "scope": "World",
    "isDarkLogo": false,
    "originalRssUrl": "https://yle.fi/rss/t/18-213332/fi"
  },
  {
    "title": "Rubio: Grönlanti kuuluu Tanskalle ”toistaiseksi”",
    "link": "https://yle.fi/a/74-20229679?origin=rss",
    "pubDate": "2026-06-03T17:57:22.000Z",
    "content": "Yhdysvaltain presidentti Donald Trump on toistuvasti vaatinut saada Grönlantia Yhdysvaltojen osaksi",
    "snippet": "Yhdysvaltain presidentti Donald Trump on toistuvasti vaatinut saada Grönlantia Yhdysvaltojen osaksi",
    "creator": "",
    "sourceTitle": "Yle | Kansainvälinen politiikka",
    "sheetCategory": "Politics + Public sector",
    "enforcedImage": null,
    "sourceDescription": "Ylen uutiset aiheesta ”Kansainvälinen politiikka” nopeasti ja luotettavasti.",
    "sourceLogo": "https://www.google.com/s2/favicons?sz=128&domain=yle.fi",
    "lang": "fi",
    "scope": "World",
    "isDarkLogo": false,
    "originalRssUrl": "https://yle.fi/rss/t/18-213332/fi"
  },
  {
    "title": "Itävalta ja Portugali valittiin YK:n turvallisuusneuvostoon",
    "link": "https://yle.fi/a/74-20229669?origin=rss",
    "pubDate": "2026-06-03T16:16:38.000Z",
    "content": "<html><head></head><body></body></html>",
    "snippet": "",
    "creator": "",
    "sourceTitle": "Yle | Kansainvälinen politiikka",
    "sheetCategory": "Politics + Public sector",
    "enforcedImage": null,
    "sourceDescription": "Ylen uutiset aiheesta ”Kansainvälinen politiikka” nopeasti ja luotettavasti.",
    "sourceLogo": "https://www.google.com/s2/favicons?sz=128&domain=yle.fi",
    "lang": "fi",
    "scope": "World",
    "isDarkLogo": false,
    "originalRssUrl": "https://yle.fi/rss/t/18-213332/fi"
  },
  {
    "title": "Saksa pyrkii turvallisuusneuvoston vaihtuvaksi jäseneksi, äänestys tänään YK:ssa",
    "link": "https://yle.fi/a/74-20229623?origin=rss",
    "pubDate": "2026-06-03T12:04:49.000Z",
    "content": "<html><head></head><body></body></html>",
    "snippet": "",
    "creator": "",
    "sourceTitle": "Yle | Kansainvälinen politiikka",
    "sheetCategory": "Politics + Public sector",
    "enforcedImage": null,
    "sourceDescription": "Ylen uutiset aiheesta ”Kansainvälinen politiikka” nopeasti ja luotettavasti.",
    "sourceLogo": "https://www.google.com/s2/favicons?sz=128&domain=yle.fi",
    "lang": "fi",
    "scope": "World",
    "isDarkLogo": false,
    "originalRssUrl": "https://yle.fi/rss/t/18-213332/fi"
  },
  {
    "title": "Suomi toimii OECD:n ministerikokouksen puheenjohtajamaana Pariisissa",
    "link": "https://yle.fi/a/74-20229471?origin=rss",
    "pubDate": "2026-06-02T23:35:45.000Z",
    "content": "<html><head></head><body></body></html>",
    "snippet": "",
    "creator": "",
    "sourceTitle": "Yle | Kansainvälinen politiikka",
    "sheetCategory": "Politics + Public sector",
    "enforcedImage": null,
    "sourceDescription": "Ylen uutiset aiheesta ”Kansainvälinen politiikka” nopeasti ja luotettavasti.",
    "sourceLogo": "https://www.google.com/s2/favicons?sz=128&domain=yle.fi",
    "lang": "fi",
    "scope": "World",
    "isDarkLogo": false,
    "originalRssUrl": "https://yle.fi/rss/t/18-213332/fi"
  },
  {
    "title": "EU pääsi sopuun maahanmuuttopolitiikan tiukennuksista – petaa palautuskeskusten perustamista EU:n ulkopuolelle",
    "link": "https://yle.fi/a/74-20229244?origin=rss",
    "pubDate": "2026-06-01T19:47:48.000Z",
    "content": "<html><head></head><body></body></html>",
    "snippet": "",
    "creator": "",
    "sourceTitle": "Yle | Kansainvälinen politiikka",
    "sheetCategory": "Politics + Public sector",
    "enforcedImage": null,
    "sourceDescription": "Ylen uutiset aiheesta ”Kansainvälinen politiikka” nopeasti ja luotettavasti.",
    "sourceLogo": "https://www.google.com/s2/favicons?sz=128&domain=yle.fi",
    "lang": "fi",
    "scope": "World",
    "isDarkLogo": false,
    "originalRssUrl": "https://yle.fi/rss/t/18-213332/fi"
  },
  {
    "title": "Espanjan Pedro Sanchezia ympäröivät kotimaassa korruptioskandaalit",
    "link": "https://yle.fi/a/74-20229094?origin=rss",
    "pubDate": "2026-06-01T08:10:56.000Z",
    "content": "Eurooppalaisen EUobserver-verkkolehden päätoimittaja Elena Sanchez Nicolas näkee, että ulkomailla ei usein ymmärretä espanjalaisen politiikan monimutkaisuutta.",
    "snippet": "Eurooppalaisen EUobserver-verkkolehden päätoimittaja Elena Sanchez Nicolas näkee, että ulkomailla ei usein ymmärretä espanjalaisen politiikan monimutkaisuutta.",
    "creator": "",
    "sourceTitle": "Yle | Kansainvälinen politiikka",
    "sheetCategory": "Politics + Public sector",
    "enforcedImage": null,
    "sourceDescription": "Ylen uutiset aiheesta ”Kansainvälinen politiikka” nopeasti ja luotettavasti.",
    "sourceLogo": "https://www.google.com/s2/favicons?sz=128&domain=yle.fi",
    "lang": "fi",
    "scope": "World",
    "isDarkLogo": false,
    "originalRssUrl": "https://yle.fi/rss/t/18-213332/fi"
  },
  {
    "title": "Guyanalle tulossa ennätysmäinen öljytili",
    "link": "https://yle.fi/a/74-20228961?origin=rss",
    "pubDate": "2026-05-31T04:25:58.000Z",
    "content": "<html><head></head><body></body></html>",
    "snippet": "",
    "creator": "",
    "sourceTitle": "Yle | Kansainvälinen politiikka",
    "sheetCategory": "Politics + Public sector",
    "enforcedImage": null,
    "sourceDescription": "Ylen uutiset aiheesta ”Kansainvälinen politiikka” nopeasti ja luotettavasti.",
    "sourceLogo": "https://www.google.com/s2/favicons?sz=128&domain=yle.fi",
    "lang": "fi",
    "scope": "World",
    "isDarkLogo": false,
    "originalRssUrl": "https://yle.fi/rss/t/18-213332/fi"
  }
]